continuing_education/__init__.py
continuing_education/checkpoint_manager.py
continuing_education/checkpoint_registry.py
continuing_education/continuing_trainer.py
continuing_education-0.0.3a1.dist-info/LICENSE
continuing_education-0.0.3a1.dist-info/METADATA
continuing_education-0.0.3a1.dist-info/WHEEL
continuing_education-0.0.3a1.dist-info/top_level.txt
continuing_education-0.0.3a1.dist-info/RECORD
